lips/__init__.py
lips/invariants.py
lips/particle.py
lips/particles.py
lips/particles_compute.py
lips/particles_eval.py
lips/particles_slices.py
lips/particles_variety.py
lips/symmetries.py
lips/tools.py
lips/version.py
lips/algebraic_geometry/__init__.py
lips/algebraic_geometry/covariant_ideal.py
lips/algebraic_geometry/invariant_ideal.py
lips/algebraic_geometry/particles_singular_variety.py
lips/algebraic_geometry/tools.py
lips/fields/__init__.py
lips/fields/field.py
lips/fields/gaussian_rationals.py
lips/hardcoded_limits/DoubleCollinearLimit_D_and_S_a.py
lips/hardcoded_limits/DoubleCollinearLimit_D_and_S_e.py
lips/hardcoded_limits/__init__.py
lips/hardcoded_limits/particles_set.py
lips/hardcoded_limits/particles_set_pair.py
lips-0.5.1.dist-info/LICENSE.txt
lips-0.5.1.dist-info/METADATA
lips-0.5.1.dist-info/WHEEL
lips-0.5.1.dist-info/top_level.txt
lips-0.5.1.dist-info/RECORD
