Metadata-Version: 2.1
Name: lips
Version: 0.5.1
Summary: Lorentz Invariant Phase Space
Home-page: https://github.com/GDeLaurentis/lips
Download-URL: https://github.com/GDeLaurentis/lips/archive/v0.5.1.tar.gz
Author: Giuseppe De Laurentis
Author-email: g.dl@hotmail.it
License: GNU General Public License v3.0
Project-URL: Documentation, https://gdelaurentis.github.io/lips/
Project-URL: Issues, https://github.com/GDeLaurentis/lips/issues
Keywords: lips,Lorentz Invariant Phase Space,Spinor Helicity
Classifier: Development Status :: 4 - Beta
Classifier: Intended Audience :: Science/Research
Classifier: Topic :: Scientific/Engineering :: Physics
Classifier: License :: OSI Approved :: GNU General Public License v3 (GPLv3)
Classifier: Programming Language :: Python :: 3.9
Classifier: Programming Language :: Python :: 3.10
Classifier: Programming Language :: Python :: 3.11
Classifier: Programming Language :: Python :: 3.12
Classifier: Programming Language :: Python :: 3.13
License-File: LICENSE.txt
Requires-Dist: mpmath
Requires-Dist: numpy
Requires-Dist: pyadic
Requires-Dist: sympy
Requires-Dist: syngular
